[
{
"provinsi": "Aceh",
"statusIntegrasi": "Proses Integrasi",
"nomorPerda": "-",
"linkPerda": "",
"statusRZWP3K": "Perda",
"riwayat": "Dalam proses integrasi RTRW dan MTPP."
},
{
"provinsi": "Bali",
"statusIntegrasi": "Terintegrasi",
"nomorPerda": "Perda No. 2 Tahun 2023",
"linkPerda": "",
"statusRZWP3K": "-",
"riwayat": "Perda RTRW telah mengintegrasikan muatan ruang laut."
},
{
"provinsi": "Banten",
"statusIntegrasi": "Terintegrasi",
"nomorPerda": "-",
"linkPerda": "",
"statusRZWP3K": "-",
"riwayat": ""
},
{
"provinsi": "Bengkulu",
"statusIntegrasi": "Terintegrasi",
"nomorPerda": "-",
"linkPerda": "",
"statusRZWP3K": "-",
"riwayat": ""
},
{
"provinsi": "Daerah Istimewa Yogyakarta",
"statusIntegrasi": "Terintegrasi",
"nomorPerda": "-",
"linkPerda": "",
"statusRZWP3K": "-",
"riwayat": ""
},
{
"provinsi": "DKI Jakarta",
"statusIntegrasi": "Terintegrasi",
"nomorPerda": "-",
"linkPerda": "",
"statusRZWP3K": "-",
"riwayat": ""
},
{
"provinsi": "Gorontalo",
"statusIntegrasi": "Terintegrasi",
"nomorPerda": "-",
"linkPerda": "",
"statusRZWP3K": "-",
"riwayat": ""
},
{
"provinsi": "Jambi",
"statusIntegrasi": "Terintegrasi",
"nomorPerda": "-",
"linkPerda": "",
"statusRZWP3K": "-",
"riwayat": ""
},
{
"provinsi": "Jawa Barat",
"statusIntegrasi": "Terintegrasi",
"nomorPerda": "-",
"linkPerda": "",
"statusRZWP3K": "-",
"riwayat": ""
},
{
"provinsi": "Jawa Tengah",
"statusIntegrasi": "Terintegrasi",
"nomorPerda": "-",
"linkPerda": "",
"statusRZWP3K": "-",
"riwayat": ""
},
{
"provinsi": "Jawa Timur",
"statusIntegrasi": "Terintegrasi",
"nomorPerda": "-",
"linkPerda": "",
"statusRZWP3K": "-",
"riwayat": ""
},
{
"provinsi": "Kalimantan Barat",
"statusIntegrasi": "Terintegrasi",
"nomorPerda": "-",
"linkPerda": "",
"statusRZWP3K": "-",
"riwayat": ""
},
{
"provinsi": "Kalimantan Selatan",
"statusIntegrasi": "Terintegrasi",
"nomorPerda": "-",
"linkPerda": "",
"statusRZWP3K": "-",
"riwayat": ""
},
{
"provinsi": "Kalimantan Tengah",
"statusIntegrasi": "Proses Integrasi",
"nomorPerda": "-",
"linkPerda": "",
"statusRZWP3K": "-",
"riwayat": ""
},
{
"provinsi": "Kalimantan Timur",
"statusIntegrasi": "Terintegrasi",
"nomorPerda": "-",
"linkPerda": "",
"statusRZWP3K": "-",
"riwayat": ""
},
{
"provinsi": "Kalimantan Utara",
"statusIntegrasi": "Proses Integrasi",
"nomorPerda": "-",
"linkPerda": "",
"statusRZWP3K": "-",
"riwayat": ""
},
{
"provinsi": "Kepulauan Bangka Belitung",
"statusIntegrasi": "Proses Integrasi",
"nomorPerda": "-",
"linkPerda": "",
"statusRZWP3K": "-",
"riwayat": ""
},
{
"provinsi": "Kepulauan Riau",
"statusIntegrasi": "Penyusunan Materi Teknis",
"nomorPerda": "-",
"linkPerda": "",
"statusRZWP3K": "-",
"riwayat": ""
},
{
"provinsi": "Lampung",
"statusIntegrasi": "Terintegrasi",
"nomorPerda": "-",
"linkPerda": "",
"statusRZWP3K": "-",
"riwayat": ""
},
{
"provinsi": "Maluku",
"statusIntegrasi": "Terintegrasi",
"nomorPerda": "-",
"linkPerda": "",
"statusRZWP3K": "-",
"riwayat": ""
},
{
"provinsi": "Maluku Utara",
"statusIntegrasi": "Terintegrasi",
"nomorPerda": "-",
"linkPerda": "",
"statusRZWP3K": "-",
"riwayat": ""
},
{
"provinsi": "Nusa Tenggara Barat",
"statusIntegrasi": "Terintegrasi",
"nomorPerda": "-",
"linkPerda": "",
"statusRZWP3K": "-",
"riwayat": ""
},
{
"provinsi": "Nusa Tenggara Timur",
"statusIntegrasi": "Terintegrasi",
"nomorPerda": "-",
"linkPerda": "",
"statusRZWP3K": "-",
"riwayat": ""
},
{
"provinsi": "Papua",
"statusIntegrasi": "Terintegrasi",
"nomorPerda": "-",
"linkPerda": "",
"statusRZWP3K": "-",
"riwayat": ""
},
{
"provinsi": "Papua Barat",
"statusIntegrasi": "Terintegrasi",
"nomorPerda": "-",
"linkPerda": "",
"statusRZWP3K": "-",
"riwayat": ""
},
{
"provinsi": "Papua Barat Daya",
"statusIntegrasi": "Penyusunan Materi Teknis",
"nomorPerda": "-",
"linkPerda": "",
"statusRZWP3K": "-",
"riwayat": ""
},
{
"provinsi": "Papua Pegunungan",
"statusIntegrasi": "Tidak Memiliki Wilayah Laut",
"nomorPerda": "-",
"linkPerda": "",
"statusRZWP3K": "-",
"riwayat": ""
},
{
"provinsi": "Papua Selatan",
"statusIntegrasi": "Terintegrasi",
"nomorPerda": "-",
"linkPerda": "",
"statusRZWP3K": "-",
"riwayat": ""
},
{
"provinsi": "Papua Tengah",
"statusIntegrasi": "Proses Integrasi",
"nomorPerda": "-",
"linkPerda": "",
"statusRZWP3K": "-",
"riwayat": ""
},
{
"provinsi": "Riau",
"statusIntegrasi": "Proses Integrasi",
"nomorPerda": "-",
"linkPerda": "",
"statusRZWP3K": "-",
"riwayat": ""
},
{
"provinsi": "Sulawesi Barat",
"statusIntegrasi": "Proses Integrasi",
"nomorPerda": "-",
"linkPerda": "",
"statusRZWP3K": "-",
"riwayat": ""
},
{
"provinsi": "Sulawesi Selatan",
"statusIntegrasi": "Terintegrasi",
"nomorPerda": "-",
"linkPerda": "",
"statusRZWP3K": "-",
"riwayat": ""
},
{
"provinsi": "Sulawesi Tengah",
"statusIntegrasi": "Terintegrasi",
"nomorPerda": "-",
"linkPerda": "",
"statusRZWP3K": "-",
"riwayat": ""
},
{
"provinsi": "Sulawesi Tenggara",
"statusIntegrasi": "Proses Integrasi",
"nomorPerda": "-",
"linkPerda": "",
"statusRZWP3K": "-",
"riwayat": ""
},
{
"provinsi": "Sulawesi Utara",
"statusIntegrasi": "Proses Integrasi",
"nomorPerda": "-",
"linkPerda": "",
"statusRZWP3K": "-",
"riwayat": ""
},
{
"provinsi": "Sumatera Barat",
"statusIntegrasi": "Terintegrasi",
"nomorPerda": "-",
"linkPerda": "",
"statusRZWP3K": "-",
"riwayat": ""
},
{
"provinsi": "Sumatera Selatan",
"statusIntegrasi": "Terintegrasi",
"nomorPerda": "-",
"linkPerda": "",
"statusRZWP3K": "-",
"riwayat": ""
},
{
"provinsi": "Sumatera Utara",
"statusIntegrasi": "Proses Integrasi",
"nomorPerda": "-",
"linkPerda": "",
"statusRZWP3K": "-",
"riwayat": ""
},
{
"provinsi": "Papua Pegunungan",
"statusIntegrasi": "-",
"nomorPerda": "-",
"linkPerda": "",
"statusRZWP3K": "-",
"riwayat": ""
}
]
